openrouter_inspector/__init__.py
openrouter_inspector/__main__.py
openrouter_inspector/_version.py
openrouter_inspector/cache.py
openrouter_inspector/cli.py
openrouter_inspector/client.py
openrouter_inspector/exceptions.py
openrouter_inspector/models.py
openrouter_inspector/services.py
openrouter_inspector/utils.py
openrouter_inspector/commands/__init__.py
openrouter_inspector/commands/base_command.py
openrouter_inspector/commands/benchmark_command.py
openrouter_inspector/commands/check_command.py
openrouter_inspector/commands/endpoints_command.py
openrouter_inspector/commands/list_command.py
openrouter_inspector/commands/ping_command.py
openrouter_inspector/formatters/__init__.py
openrouter_inspector/formatters/base.py
openrouter_inspector/formatters/json_formatter.py
openrouter_inspector/formatters/table_formatter.py
openrouter_inspector/handlers/__init__.py
openrouter_inspector/handlers/endpoint_handler.py
openrouter_inspector/handlers/model_handler.py
openrouter_inspector/handlers/provider_handler.py
openrouter_inspector-0.1.9.dist-info/METADATA
openrouter_inspector-0.1.9.dist-info/WHEEL
openrouter_inspector-0.1.9.dist-info/entry_points.txt
openrouter_inspector-0.1.9.dist-info/licenses/LICENSE
openrouter_inspector-0.1.9.dist-info/RECORD
