Metadata-Version: 2.4
Name: openrouter-inspector
Version: 0.1.9
Summary: A command-line tool for querying OpenRouter AI models and providers
Project-URL: Homepage, https://github.com/matdev83/openrouter-inspector/
Project-URL: Repository, https://github.com/matdev83/openrouter-inspector/
Project-URL: Documentation, https://github.com/matdev83/openrouter-inspector#readme
Project-URL: Bug Tracker, https://github.com/matdev83/openrouter-inspector/issues
Author-email: "Mateusz B." <matdev83@github.com>
Maintainer-email: "Mateusz B." <matdev83@github.com>
License: MIT License
License-File: LICENSE
Keywords: ai,api,cli,models,openrouter
Classifier: Development Status :: 3 - Alpha
Classifier: Environment :: Console
Classifier: Intended Audience :: Developers
Classifier: Intended Audience :: System Administrators
Classifier: License :: OSI Approved :: MIT License
Classifier: Operating System :: OS Independent
Classifier: Programming Language :: Python :: 3
Classifier: Programming Language :: Python :: 3.10
Classifier: Programming Language :: Python :: 3.11
Classifier: Programming Language :: Python :: 3.12
Classifier: Topic :: Internet :: WWW/HTTP :: HTTP Servers
Classifier: Topic :: Scientific/Engineering :: Artificial Intelligence
Classifier: Topic :: Software Development :: Libraries :: Python Modules
Classifier: Topic :: System :: Monitoring
Classifier: Topic :: Utilities
Classifier: Typing :: Typed
Requires-Python: >=3.10
Requires-Dist: click>=8.0.0
Requires-Dist: httpx>=0.24.0
Requires-Dist: pydantic>=2.0.0
Requires-Dist: rich>=13.0.0
Requires-Dist: tiktoken>=0.5.0
Requires-Dist: tomli>=2.0.1; python_version < '3.11'
Provides-Extra: all
Requires-Dist: bandit[toml]>=1.7.5; extra == 'all'
Requires-Dist: black>=23.0.0; extra == 'all'
Requires-Dist: build>=0.10.0; extra == 'all'
Requires-Dist: hatch-vcs>=0.3.0; extra == 'all'
Requires-Dist: hatch>=1.9.0; extra == 'all'
Requires-Dist: hatchling>=1.18.0; extra == 'all'
Requires-Dist: hypothesis>=6.0.0; extra == 'all'
Requires-Dist: mkdocs-material>=9.0.0; extra == 'all'
Requires-Dist: mkdocs>=1.5.0; extra == 'all'
Requires-Dist: mkdocstrings[python]>=0.20.0; extra == 'all'
Requires-Dist: mypy>=1.0.0; extra == 'all'
Requires-Dist: pre-commit>=3.0.0; extra == 'all'
Requires-Dist: pytest-asyncio>=0.21.0; extra == 'all'
Requires-Dist: pytest-cov>=4.0.0; extra == 'all'
Requires-Dist: pytest-httpx>=0.21.0; extra == 'all'
Requires-Dist: pytest>=7.0.0; extra == 'all'
Requires-Dist: ruff>=0.1.0; extra == 'all'
Requires-Dist: safety>=3.2.0; extra == 'all'
Requires-Dist: twine>=4.0.0; extra == 'all'
Requires-Dist: vulture>=2.0; extra == 'all'
Requires-Dist: wheel>=0.40.0; extra == 'all'
Provides-Extra: build
Requires-Dist: build>=0.10.0; extra == 'build'
Requires-Dist: hatch-vcs>=0.3.0; extra == 'build'
Requires-Dist: hatch>=1.9.0; extra == 'build'
Requires-Dist: hatchling>=1.18.0; extra == 'build'
Requires-Dist: twine>=4.0.0; extra == 'build'
Requires-Dist: wheel>=0.40.0; extra == 'build'
Provides-Extra: complete
Requires-Dist: bandit[toml]>=1.7.5; extra == 'complete'
Requires-Dist: black>=23.0.0; extra == 'complete'
Requires-Dist: build>=0.10.0; extra == 'complete'
Requires-Dist: hatch-vcs>=0.3.0; extra == 'complete'
Requires-Dist: hatch>=1.9.0; extra == 'complete'
Requires-Dist: hatchling>=1.18.0; extra == 'complete'
Requires-Dist: hypothesis>=6.0.0; extra == 'complete'
Requires-Dist: mkdocs-material>=9.0.0; extra == 'complete'
Requires-Dist: mkdocs>=1.5.0; extra == 'complete'
Requires-Dist: mkdocstrings[python]>=0.20.0; extra == 'complete'
Requires-Dist: mypy>=1.0.0; extra == 'complete'
Requires-Dist: pre-commit>=3.0.0; extra == 'complete'
Requires-Dist: pytest-asyncio>=0.21.0; extra == 'complete'
Requires-Dist: pytest-cov>=4.0.0; extra == 'complete'
Requires-Dist: pytest-httpx>=0.21.0; extra == 'complete'
Requires-Dist: pytest>=7.0.0; extra == 'complete'
Requires-Dist: ruff>=0.1.0; extra == 'complete'
Requires-Dist: safety>=3.2.0; extra == 'complete'
Requires-Dist: twine>=4.0.0; extra == 'complete'
Requires-Dist: vulture>=2.0; extra == 'complete'
Requires-Dist: wheel>=0.40.0; extra == 'complete'
Provides-Extra: dev
Requires-Dist: bandit[toml]>=1.7.5; extra == 'dev'
Requires-Dist: black>=23.0.0; extra == 'dev'
Requires-Dist: mypy>=1.0.0; extra == 'dev'
Requires-Dist: pre-commit>=3.0.0; extra == 'dev'
Requires-Dist: ruff>=0.1.0; extra == 'dev'
Requires-Dist: safety>=3.2.0; extra == 'dev'
Requires-Dist: vulture>=2.0; extra == 'dev'
Provides-Extra: docs
Requires-Dist: mkdocs-material>=9.0.0; extra == 'docs'
Requires-Dist: mkdocs>=1.5.0; extra == 'docs'
Requires-Dist: mkdocstrings[python]>=0.20.0; extra == 'docs'
Provides-Extra: security
Requires-Dist: bandit[toml]>=1.7.5; extra == 'security'
Requires-Dist: safety>=3.2.0; extra == 'security'
Provides-Extra: test
Requires-Dist: hypothesis>=6.0.0; extra == 'test'
Requires-Dist: pytest-asyncio>=0.21.0; extra == 'test'
Requires-Dist: pytest-cov>=4.0.0; extra == 'test'
Requires-Dist: pytest-httpx>=0.21.0; extra == 'test'
Requires-Dist: pytest>=7.0.0; extra == 'test'
